{
  "node": {
    "7f903388c5bfb84a0899a582bf202a091f2a87aff4": {
      "workers": {
        "app/_not-found/page": {
          "moduleId": "(rsc)/./node_modules/next/dist/build/webpack/loaders/next-flight-action-entry-loader.js?actions=%5B%5B%22D%3A%5C%5Csportsdunia%5C%5Cnews-blog%5C%5Cnode_modules%5C%5C%40clerk%5C%5Cnextjs%5C%5Cdist%5C%5Cesm%5C%5Capp-router%5C%5Ckeyless-actions.js%22%2C%5B%7B%22id%22%3A%227f903388c5bfb84a0899a582bf202a091f2a87aff4%22%2C%22exportedName%22%3A%22syncKeylessConfigAction%22%7D%2C%7B%22id%22%3A%227fb8829dfa76de178875025ebc127d03d7b67dcf70%22%2C%22exportedName%22%3A%22deleteKeylessAction%22%7D%2C%7B%22id%22%3A%227ffc20224e15810660c0143dd4c10776a9c64b9638%22%2C%22exportedName%22%3A%22createOrReadKeylessAction%22%7D%5D%5D%5D&__client_imported__=!",
          "async": false
        }
      },
      "layer": {
        "app/_not-found/page": "rsc"
      }
    },
    "7fb8829dfa76de178875025ebc127d03d7b67dcf70": {
      "workers": {
        "app/_not-found/page": {
          "moduleId": "(rsc)/./node_modules/next/dist/build/webpack/loaders/next-flight-action-entry-loader.js?actions=%5B%5B%22D%3A%5C%5Csportsdunia%5C%5Cnews-blog%5C%5Cnode_modules%5C%5C%40clerk%5C%5Cnextjs%5C%5Cdist%5C%5Cesm%5C%5Capp-router%5C%5Ckeyless-actions.js%22%2C%5B%7B%22id%22%3A%227f903388c5bfb84a0899a582bf202a091f2a87aff4%22%2C%22exportedName%22%3A%22syncKeylessConfigAction%22%7D%2C%7B%22id%22%3A%227fb8829dfa76de178875025ebc127d03d7b67dcf70%22%2C%22exportedName%22%3A%22deleteKeylessAction%22%7D%2C%7B%22id%22%3A%227ffc20224e15810660c0143dd4c10776a9c64b9638%22%2C%22exportedName%22%3A%22createOrReadKeylessAction%22%7D%5D%5D%5D&__client_imported__=!",
          "async": false
        }
      },
      "layer": {
        "app/_not-found/page": "rsc"
      }
    },
    "7ffc20224e15810660c0143dd4c10776a9c64b9638": {
      "workers": {
        "app/_not-found/page": {
          "moduleId": "(rsc)/./node_modules/next/dist/build/webpack/loaders/next-flight-action-entry-loader.js?actions=%5B%5B%22D%3A%5C%5Csportsdunia%5C%5Cnews-blog%5C%5Cnode_modules%5C%5C%40clerk%5C%5Cnextjs%5C%5Cdist%5C%5Cesm%5C%5Capp-router%5C%5Ckeyless-actions.js%22%2C%5B%7B%22id%22%3A%227f903388c5bfb84a0899a582bf202a091f2a87aff4%22%2C%22exportedName%22%3A%22syncKeylessConfigAction%22%7D%2C%7B%22id%22%3A%227fb8829dfa76de178875025ebc127d03d7b67dcf70%22%2C%22exportedName%22%3A%22deleteKeylessAction%22%7D%2C%7B%22id%22%3A%227ffc20224e15810660c0143dd4c10776a9c64b9638%22%2C%22exportedName%22%3A%22createOrReadKeylessAction%22%7D%5D%5D%5D&__client_imported__=!",
          "async": false
        }
      },
      "layer": {
        "app/_not-found/page": "rsc"
      }
    },
    "7f00cfdfac906a6e91b304893394b354e59f5234cf": {
      "workers": {
        "app/_not-found/page": {
          "moduleId": "(action-browser)/./node_modules/next/dist/build/webpack/loaders/next-flight-action-entry-loader.js?actions=%5B%5B%22D%3A%5C%5Csportsdunia%5C%5Cnews-blog%5C%5Cnode_modules%5C%5C%40clerk%5C%5Cnextjs%5C%5Cdist%5C%5Cesm%5C%5Capp-router%5C%5Cserver-actions.js%22%2C%5B%7B%22id%22%3A%227f00cfdfac906a6e91b304893394b354e59f5234cf%22%2C%22exportedName%22%3A%22invalidateCacheAction%22%7D%5D%5D%5D&__client_imported__=true!",
          "async": false
        }
      },
      "layer": {
        "app/_not-found/page": "action-browser"
      }
    }
  },
  "edge": {},
  "encryptionKey": "QBvN1dDle1zmqc6at1PaOx4lw3rLW9yF36gz+/6mSpk="
}